ProgramAnalyze/__init__.py
ProgramAnalyze/analyze.py
ProgramAnalyze/directory_analyzer.py
programanalyze-0.1.6.dist-info/METADATA
programanalyze-0.1.6.dist-info/WHEEL
programanalyze-0.1.6.dist-info/top_level.txt
programanalyze-0.1.6.dist-info/RECORD
