Metadata-Version: 2.4
Name: ProgramAnalyze
Version: 0.1.6
